infirun/__init__.py
infirun/pipe/__init__.py
infirun/pipe/parameter.py
infirun/pipe/runner.py
infirun/pipe/sink.py
infirun/pipe/step.py
infirun/pipe/step_arg.py
infirun/pipe/test/__init__.py
infirun/pipe/test/test_parameter.py
infirun/pipe/test/test_runner.py
infirun/pipe/test/test_sink.py
infirun/pipe/test/test_step.py
infirun/pipe/test/test_step_arg.py
infirun/train/__init__.py
infirun/train/trainer.py
infirun/train/test/__init__.py
infirun/train/test/test_trainer.py
infirun/util/__init__.py
infirun/util/reflect.py
infirun/util/schema.py
infirun/util/schematic.py
infirun/util/test/__init__.py
infirun/util/test/test_reflect.py
infirun-0.1.0.dist-info/METADATA
infirun-0.1.0.dist-info/RECORD
infirun-0.1.0.dist-info/WHEEL
infirun-0.1.0.dist-info/top_level.txt
