Metadata-Version: 2.1
Name: infirun
Version: 0.1.0
Summary: TBA
Home-page: https://github.com/zh217/infirun.git
Author: Ziyang Hu
Author-email: hu.ziyang@cantab.net
License: MIT
Platform: UNKNOWN
